aio_odoorpc_base/__init__.py
aio_odoorpc_base/aio/__init__.py
aio_odoorpc_base/aio/common.py
aio_odoorpc_base/aio/db.py
aio_odoorpc_base/aio/object.py
aio_odoorpc_base/aio/rpc.py
aio_odoorpc_base/helpers.py
aio_odoorpc_base/protocols.py
aio_odoorpc_base/sync/__init__.py
aio_odoorpc_base/sync/common.py
aio_odoorpc_base/sync/db.py
aio_odoorpc_base/sync/object.py
aio_odoorpc_base/sync/rpc.py
aio_odoorpc_base-3.0.4.dist-info/LICENSE
aio_odoorpc_base-3.0.4.dist-info/WHEEL
aio_odoorpc_base-3.0.4.dist-info/METADATA
aio_odoorpc_base-3.0.4.dist-info/RECORD
